pytest_reporter_html1/__init__.py
pytest_reporter_html1/plugin.py
pytest_reporter_html1/templates/html1/base.html
pytest_reporter_html1/templates/html1/index.html
pytest_reporter_html1/templates/html1/module.html
pytest_reporter_html1/templates/html1/normalize.css
pytest_reporter_html1/templates/html1/style.css
pytest_reporter_html1/templates/html1/test.html
pytest_reporter_html1/templates/html1/icons/arrow.svg
pytest_reporter_html1/templates/html1/icons/nok.svg
pytest_reporter_html1/templates/html1/icons/ok.svg
pytest_reporter_html1/templates/html1/icons/skip.svg
pytest_reporter_html1-0.9.5.dist-info/licenses/LICENSE
pytest_reporter_html1-0.9.5.dist-info/METADATA
pytest_reporter_html1-0.9.5.dist-info/WHEEL
pytest_reporter_html1-0.9.5.dist-info/entry_points.txt
pytest_reporter_html1-0.9.5.dist-info/top_level.txt
pytest_reporter_html1-0.9.5.dist-info/RECORD
