Metadata-Version: 2.4
Name: pytest-reporter-html1
Version: 0.9.5
Summary: A basic HTML report template for Pytest
Author-email: Christian Sandberg <christiansandberg@me.com>
License-Expression: MIT
Project-URL: Repository, https://github.com/christiansandberg/pytest-reporter-html1.git
Project-URL: Issues, https://github.com/christiansandberg/pytest-reporter-html1/issues
Classifier: Development Status :: 4 - Beta
Classifier: Framework :: Pytest
Classifier: Intended Audience :: Developers
Classifier: Topic :: Software Development :: Testing
Classifier: Topic :: Text Processing :: Markup :: HTML
Classifier: Operating System :: OS Independent
Classifier: Programming Language :: Python :: 3
Requires-Python: >=3.10
License-File: LICENSE
Requires-Dist: pytest-reporter>=0.4.0
Requires-Dist: Jinja2
Requires-Dist: ansi2html>=1.3.0
Requires-Dist: htmlmin2
Requires-Dist: docutils>=0.22
Dynamic: license-file
